[
  {
    "featureType": "administrative",
    "elementType": "labels.text.fill",
    "stylers": [
      { "visibility": "off" }
    ]
  },{
    "featureType": "water",
    "elementType": "labels",
    "stylers": [
      { "visibility": "off" }
    ]
  },{
    "featureType": "road",
    "stylers": [
      { "visibility": "off" }
    ]
  },{
    "featureType": "poi",
    "stylers": [
      { "visibility": "off" }
    ]
  },{
    "featureType": "administrative.locality",
    "stylers": [
      { "visibility": "off" }
    ]
  },{
    "featureType": "administrative.country",
    "elementType": "labels",
    "stylers": [
      { "visibility": "off" }
    ]
  },{
    "featureType": "administrative.province",
    "stylers": [
      { "visibility": "off" }
    ]
  },{
    "featureType": "transit",
    "stylers": [
      { "visibility": "off" }
    ]
  },{
    "featureType": "landscape",
    "stylers": [
      { "visibility": "off" }
    ]
  },{
    "featureType": "administrative.country",
    "stylers": [
      { "color": "#FFC7E6" }
    ]
  },{
    "featureType": "water",
    "stylers": [
      { "color": "#99FAF0" }
    ]
  },{
    "featureType": "landscape",
    "stylers": [
      { "visibility": "on" },
      { "color": "#FFEDF7" }
    ]
  },{
    "featureType": "administrative",
    "elementType": "geometry.fill",
    "stylers": [
      { "weight": 1 },
      { "color": "#478080" },
      { "visibility": "off" }
    ]
  },{
  }
]